[
    {
        "fecha_resolucion": "10/24/2022 11:14:39",
        "area": "MONITOREO DE CONDICION",
        "nombre": "FALCON GRANDE, ABRAHAM",
        "correo": "afalcon@marco.com.pe",
        "jefe_directo": "Niltón Gutiérrez",
        "cargo": "ANALISTA DE LABORATORIO SENIOR",
        "fecha_evaluacion": "24/10/2022",
        "competencia_comunicacion": "Cumple",
        "competencia_trabajo_equipo": "Destacado",
        "competencia_productividad": "Destacado",
        "competencia_flexibilidad": "Cumple",
        "competencia_iniciativa": "Destacado",
        "competencia_tolerancia_presion": "Cumple",
        "competencia_planificacion_organizacion": "Cumple",
        "feedback_objetivo": "Ligeramente por encima de lo esperado: En ocasiones supera los objetivos propuestos para su puesto. Muestra un desempeño satisfactorio con algunas oportunidades de logro.",
        "feedback_comentario": "COLABORADOR CON ALTO GRADO DE RESPONSABILIDAD EN EL ÁREA. EN PROCESO DE APRENDIZAJE DEL SISTEMA ADMINISTRATIVO DE LA EMPRESA, PARA MEJORAR EL TEMA DE COMUNICACIÓN CONSTANTE PARA INFORMACIÓN DE LOS CUMPLIMIENTOS EN EL AREA.",
        "grupo_ocupasional": "4",
        "comunicacion": "15",
        "liderazgo": "17",
        "trabajo_en_equipo": "17",
        "productividad": "15",
        "flexibilidad": "17",
        "iniciativa": "15",
        "tolerancia_presion": "15",
        "planificacion_organizacion": "17",
        "puntaje_competencia": "111",
        "nota_competencia": "17",
        "categoria_competencia": "17",
        "categoria_objetivo": "Ligeramente por encima de lo esperado",
        "nota_objetivo": "17",
        "promedio": "17",
        "nota_objetivo1": "17",
        "nota_objetivo2": "17",
        "nivel_general": "Destacado",
        "nivel_general_nota": "17",
        "evaluador": "Se debe completar",
        "razon_social": "MP"
    },
    {
        "fecha_resolucion": "10/26/2022 23:02:40",
        "area": "LUBRICACION MINERIA",
        "nombre": "DIAZ MARTINEZ, JUAN LEANDRO",
        "correo": "jdiaz@marco.com.pe",
        "jefe_directo": "Juan David Narva",
        "cargo": "PLANNER DE MANTENIMIENTO",
        "fecha_evaluacion": "26/10/2022",
        "competencia_comunicacion": "Destacado",
        "competencia_trabajo_equipo": "Destacado",
        "competencia_productividad": "Excelente",
        "competencia_flexibilidad": "Destacado",
        "competencia_iniciativa": "Destacado",
        "competencia_tolerancia_presion": "Destacado",
        "competencia_planificacion_organizacion": "Destacado",
        "feedback_objetivo": "Ligeramente por encima de lo esperado: En ocasiones supera los objetivos propuestos para su puesto. Muestra un desempeño satisfactorio con algunas oportunidades de logro.",
        "feedback_comentario": "POTENCIAR SU LIDERAZGO CON EL PERSONAL TÉCNICO, PARA CUMPLIR CON LOS OBJETIVOS DEL EQUIPO Y LA EMPRESA.",
        "grupo_ocupasional": "4",
        "comunicacion": "17",
        "liderazgo": "17",
        "trabajo_en_equipo": "19",
        "productividad": "17",
        "flexibilidad": "17",
        "iniciativa": "17",
        "tolerancia_presion": "17",
        "planificacion_organizacion": "17",
        "puntaje_competencia": "121",
        "nota_competencia": "19",
        "categoria_competencia": "19",
        "categoria_objetivo": "Ligeramente por encima de lo esperado",
        "nota_objetivo": "17",
        "promedio": "19",
        "nota_objetivo1": "18",
        "nota_objetivo2": "18",
        "nivel_general": "Excelente",
        "nivel_general_nota": "19",
        "evaluador": "Se debe completar",
        "razon_social": "MP"
    },
    {
        "fecha_resolucion": "10/28/2022 15:06:35",
        "area": "FINANZAS",
        "nombre": "ESCALANTE CELIS, EVA CECILIA",
        "correo": "eescalante@marco.com.pe",
        "jefe_directo": "Christian Dawson",
        "cargo": "ANALISTA DE PROCESOS",
        "fecha_evaluacion": "28/10/2022",
        "competencia_comunicacion": "Cumple",
        "competencia_trabajo_equipo": "Destacado",
        "competencia_productividad": "Destacado",
        "competencia_flexibilidad": "Destacado",
        "competencia_iniciativa": "Destacado",
        "competencia_tolerancia_presion": "Cumple",
        "competencia_planificacion_organizacion": "Cumple",
        "feedback_objetivo": "Ligeramente por encima de lo esperado: En ocasiones supera los objetivos propuestos para su puesto. Muestra un desempeño satisfactorio con algunas oportunidades de logro.",
        "feedback_comentario": "Muy contento con el desempeño de Eva en un puesto que requiere muchas adaptabilidad y un conocimiento profundo de la empresa. Muy buena disposición a aprender y ganas de sacar las cosas adelante. Puede mejorar sus concocimientos informáticos.",
        "grupo_ocupasional": "4",
        "comunicacion": "15",
        "liderazgo": "17",
        "trabajo_en_equipo": "17",
        "productividad": "17",
        "flexibilidad": "17",
        "iniciativa": "15",
        "tolerancia_presion": "15",
        "planificacion_organizacion": "17",
        "puntaje_competencia": "113",
        "nota_competencia": "17",
        "categoria_competencia": "17",
        "categoria_objetivo": "Ligeramente por encima de lo esperado",
        "nota_objetivo": "17",
        "promedio": "17",
        "nota_objetivo1": "17",
        "nota_objetivo2": "17",
        "nivel_general": "Destacado",
        "nivel_general_nota": "17",
        "evaluador": "Se debe completar",
        "razon_social": "MP"
    },
    {
        "fecha_resolucion": "11/2/2022 11:53:54",
        "area": "COMPRAS",
        "nombre": "GALLO SOSA, JORGE LUIS",
        "correo": "jgallo@marco.com.pe",
        "jefe_directo": "Guisela Reyna",
        "cargo": "PLANNER SENIOR",
        "fecha_evaluacion": "02/11/2022",
        "competencia_comunicacion": "Destacado",
        "competencia_trabajo_equipo": "Cumple",
        "competencia_productividad": "Cumple",
        "competencia_flexibilidad": "Cumple",
        "competencia_iniciativa": "Cumple",
        "competencia_tolerancia_presion": "Destacado",
        "competencia_planificacion_organizacion": "Cumple",
        "feedback_objetivo": "Ligeramente por encima de lo esperado: En ocasiones supera los objetivos propuestos para su puesto. Muestra un desempeño satisfactorio con algunas oportunidades de logro.",
        "feedback_comentario": "\"Jorge, es la persona que debe liderar al equipo de Planeamiento, aún considero está en ese proceso. "
    },
    {
        "fecha_resolucion": " El cuenta con las habilidades duras para su posición actual y en muchas de ellas rescato su empeño en cada día aprender y preparase más."
    },
    {
        "fecha_resolucion": " Auguro para Jorge un excelente futuro profesional, sólo le pido que también fortalezca las habilidades blandas, que estoy segura ha identificado y puede seguir mejorando.\"",
        "area": "4",
        "nombre": "17",
        "correo": "15",
        "jefe_directo": "15",
        "cargo": "15",
        "fecha_evaluacion": "15",
        "competencia_comunicacion": "17",
        "competencia_trabajo_equipo": "15",
        "competencia_productividad": "17",
        "competencia_flexibilidad": "109",
        "competencia_iniciativa": "17",
        "competencia_tolerancia_presion": "17",
        "competencia_planificacion_organizacion": "Destacado",
        "feedback_objetivo": "17",
        "feedback_comentario": "17",
        "grupo_ocupasional": "Ligeramente por encima de lo esperado",
        "comunicacion": "17",
        "liderazgo": "17",
        "trabajo_en_equipo": "17",
        "productividad": "Destacado",
        "flexibilidad": "17",
        "iniciativa": "Se debe completar",
        "tolerancia_presion": "MP"
    },
    {
        "fecha_resolucion": "11/2/2022 11:58:03",
        "area": "COMPRAS",
        "nombre": "MEJIA MAYAUTE, TADEO ANTONIO",
        "correo": "tmejia@marco.com.pe",
        "jefe_directo": "Guisela Reyna",
        "cargo": "PLANNER",
        "fecha_evaluacion": "02/11/2022",
        "competencia_comunicacion": "Cumple",
        "competencia_trabajo_equipo": "Destacado",
        "competencia_productividad": "Cumple",
        "competencia_flexibilidad": "Cumple",
        "competencia_iniciativa": "Destacado",
        "competencia_tolerancia_presion": "Cumple",
        "competencia_planificacion_organizacion": "Cumple",
        "feedback_objetivo": "Cumple con lo requerido: Cumple con los objetivos propuestos para su puesto. Muestra un desempeño esperado.",
        "feedback_comentario": "\"Veo en Tadeo, un profesional que cada día va creciendo y conociendo más de sus funciones y como estas influyen en los resultados que la empresa necesita."
    },
    {
        "fecha_resolucion": " Un área que considero debe fortalecer es la seguridad y decisión en sus tareas diarias, defender su posición y hacer que las cosas sucedan.\"",
        "area": "4",
        "nombre": "15",
        "correo": "17",
        "jefe_directo": "15",
        "cargo": "15",
        "fecha_evaluacion": "17",
        "competencia_comunicacion": "15",
        "competencia_trabajo_equipo": "15",
        "competencia_productividad": "15",
        "competencia_flexibilidad": "109",
        "competencia_iniciativa": "17",
        "competencia_tolerancia_presion": "17",
        "competencia_planificacion_organizacion": "Destacado",
        "feedback_objetivo": "17",
        "feedback_comentario": "15",
        "grupo_ocupasional": "Cumple con lo requerido",
        "comunicacion": "17",
        "liderazgo": "16",
        "trabajo_en_equipo": "16",
        "productividad": "Destacado",
        "flexibilidad": "17",
        "iniciativa": "Se debe completar",
        "tolerancia_presion": "MP"
    },
    {
        "fecha_resolucion": "11/2/2022 12:10:06",
        "area": "COMPRAS",
        "nombre": "PRADO CORNEJO, ANTHONY BALBUINO",
        "correo": "aprado@marco.com.pe",
        "jefe_directo": "Guisela Reyna",
        "cargo": "PLANNER",
        "fecha_evaluacion": "02/11/2022",
        "competencia_comunicacion": "Cumple",
        "competencia_trabajo_equipo": "Destacado",
        "competencia_productividad": "Destacado",
        "competencia_flexibilidad": "Destacado",
        "competencia_iniciativa": "Cumple",
        "competencia_tolerancia_presion": "Cumple",
        "competencia_planificacion_organizacion": "Destacado",
        "feedback_objetivo": "Claramente por encima de lo esperado: Frecuentemente supera los objetivos propuestos para su puesto. Muestra un desempeño que en diversos momentos es destacado.",
        "feedback_comentario": "\"Esta evaluación de Anthony, comprende tanto su puesto en Almacén, como el actual en Planeamiento."
    },
    {
        "fecha_resolucion": " Anthony es un profesional que cuenta con todos los conocimientos que pueden hacer que su trabajo sea llevado a un siguiente nivel. Una persona comprometida y buscando siempre mejorar los entregables."
    },
    {
        "fecha_resolucion": " En cuanto a habilidades blandas, considero que tiene oportunidad en mejorar la locuacidad con sus compañeros de trabajo, algo que también irá consiguiendo conforme se empodere de su actual puesto de trabajo, que exige reuniones con todos los niveles de la compañía.\"",
        "area": "4",
        "nombre": "15",
        "correo": "17",
        "jefe_directo": "17",
        "cargo": "17",
        "fecha_evaluacion": "15",
        "competencia_comunicacion": "15",
        "competencia_trabajo_equipo": "17",
        "competencia_productividad": "19",
        "competencia_flexibilidad": "113",
        "competencia_iniciativa": "17",
        "competencia_tolerancia_presion": "17",
        "competencia_planificacion_organizacion": "Destacado",
        "feedback_objetivo": "17",
        "feedback_comentario": "19",
        "grupo_ocupasional": "Claramente por encima de lo esperado",
        "comunicacion": "17",
        "liderazgo": "18",
        "trabajo_en_equipo": "18",
        "productividad": "Excelente",
        "flexibilidad": "19",
        "iniciativa": "Se debe completar",
        "tolerancia_presion": "MP"
    },
    {
        "fecha_resolucion": "11/3/2022 17:07:46",
        "area": "FINANZAS",
        "nombre": "MATOS INGA, AMELIA",
        "correo": "amattos@marco.com.pe",
        "jefe_directo": "José Carlos Granda",
        "cargo": "ANALISTA DE COBRANZA",
        "fecha_evaluacion": "03/11/2022",
        "competencia_comunicacion": "Destacado",
        "competencia_trabajo_equipo": "Destacado",
        "competencia_productividad": "Destacado",
        "competencia_flexibilidad": "Cumple",
        "competencia_iniciativa": "Destacado",
        "competencia_tolerancia_presion": "Cumple",
        "competencia_planificacion_organizacion": "Cumple",
        "feedback_objetivo": "Ligeramente por encima de lo esperado: En ocasiones supera los objetivos propuestos para su puesto. Muestra un desempeño satisfactorio con algunas oportunidades de logro.",
        "feedback_comentario": "Tiene claros los procesos y objetivos del área. Quizá podría mejorar un poco algunas formas de solicitar algunas cosas; sin embargo, en líneas generales, tiene un muy buen desempeño.",
        "grupo_ocupasional": "4",
        "comunicacion": "17",
        "liderazgo": "17",
        "trabajo_en_equipo": "17",
        "productividad": "15",
        "flexibilidad": "17",
        "iniciativa": "15",
        "tolerancia_presion": "15",
        "planificacion_organizacion": "17",
        "puntaje_competencia": "113",
        "nota_competencia": "17",
        "categoria_competencia": "17",
        "categoria_objetivo": "Ligeramente por encima de lo esperado",
        "nota_objetivo": "17",
        "promedio": "17",
        "nota_objetivo1": "17",
        "nota_objetivo2": "17",
        "nivel_general": "Destacado",
        "nivel_general_nota": "17",
        "evaluador": "Se debe completar",
        "razon_social": "MP"
    },
    {
        "fecha_resolucion": "11/3/2022 17:12:06",
        "area": "FINANZAS",
        "nombre": "MEZA RAMOS, MARIELA ROXANA",
        "correo": "mmeza@marco.com.pe",
        "jefe_directo": "José Carlos Granda",
        "cargo": "ANALISTA DE ADMINISTRACION Y FINANZAS",
        "fecha_evaluacion": "03/11/2022",
        "competencia_comunicacion": "Cumple",
        "competencia_trabajo_equipo": "Cumple",
        "competencia_productividad": "Destacado",
        "competencia_flexibilidad": "Excelente",
        "competencia_iniciativa": "Cumple",
        "competencia_tolerancia_presion": "Excelente",
        "competencia_planificacion_organizacion": "Cumple",
        "feedback_objetivo": "Cumple con lo requerido: Cumple con los objetivos propuestos para su puesto. Muestra un desempeño esperado.",
        "feedback_comentario": "Cuenta con buen manejo de los temas del área y conocimiento del negocio. Tiene un espacio de mejora en comunicar de manera un tanto más eficiente.",
        "grupo_ocupasional": "4",
        "comunicacion": "15",
        "liderazgo": "15",
        "trabajo_en_equipo": "17",
        "productividad": "19",
        "flexibilidad": "15",
        "iniciativa": "19",
        "tolerancia_presion": "15",
        "planificacion_organizacion": "15",
        "puntaje_competencia": "115",
        "nota_competencia": "17",
        "categoria_competencia": "17",
        "categoria_objetivo": "Cumple con lo requerido",
        "nota_objetivo": "15",
        "promedio": "17",
        "nota_objetivo1": "16",
        "nota_objetivo2": "16",
        "nivel_general": "Destacado",
        "nivel_general_nota": "17",
        "evaluador": "Se debe completar",
        "razon_social": "MP"
    },
    {
        "fecha_resolucion": "11/3/2022 17:17:14",
        "area": "FINANZAS",
        "nombre": "OCHOA OSORIO, ALICIA LUCILA",
        "correo": "alicia.ochoa@marco.com.pe",
        "jefe_directo": "José Carlos Granda",
        "cargo": "ANALISTA DE CREDITOS, COBRANZAS Y FACTURACION",
        "fecha_evaluacion": "03/11/2022",
        "competencia_comunicacion": "Destacado",
        "competencia_trabajo_equipo": "Excelente",
        "competencia_productividad": "Destacado",
        "competencia_flexibilidad": "Destacado",
        "competencia_iniciativa": "Destacado",
        "competencia_tolerancia_presion": "Cumple",
        "competencia_planificacion_organizacion": "Cumple",
        "feedback_objetivo": "Ligeramente por encima de lo esperado: En ocasiones supera los objetivos propuestos para su puesto. Muestra un desempeño satisfactorio con algunas oportunidades de logro.",
        "feedback_comentario": "Cuenta con un muy buen trabajo en equipo e iniciativa. Podría mejorar en organizar mejor algunas tareas para reducir carga laboral.",
        "grupo_ocupasional": "4",
        "comunicacion": "17",
        "liderazgo": "19",
        "trabajo_en_equipo": "17",
        "productividad": "17",
        "flexibilidad": "17",
        "iniciativa": "15",
        "tolerancia_presion": "15",
        "planificacion_organizacion": "17",
        "puntaje_competencia": "117",
        "nota_competencia": "17",
        "categoria_competencia": "17",
        "categoria_objetivo": "Ligeramente por encima de lo esperado",
        "nota_objetivo": "17",
        "promedio": "17",
        "nota_objetivo1": "17",
        "nota_objetivo2": "17",
        "nivel_general": "Destacado",
        "nivel_general_nota": "17",
        "evaluador": "Se debe completar",
        "razon_social": "MP"
    },
    {
        "fecha_resolucion": "11/3/2022 17:20:13",
        "area": "FINANZAS",
        "nombre": "MEDINA VALLEJOS, DARCIA KIMBERLY",
        "correo": "dmedina@marco.com.pe",
        "jefe_directo": "José Carlos Granda",
        "cargo": "ANALISTA DE CREDITOS, COBRANZAS Y FACTURACION",
        "fecha_evaluacion": "03/11/2022",
        "competencia_comunicacion": "Excelente",
        "competencia_trabajo_equipo": "Excelente",
        "competencia_productividad": "Excelente",
        "competencia_flexibilidad": "Destacado",
        "competencia_iniciativa": "Excelente",
        "competencia_tolerancia_presion": "Cumple",
        "competencia_planificacion_organizacion": "Destacado",
        "feedback_objetivo": "Claramente por encima de lo esperado: Frecuentemente supera los objetivos propuestos para su puesto. Muestra un desempeño que en diversos momentos es destacado.",
        "feedback_comentario": "Cuenta con habilidades técnicas y de trabajo en equipo muy buenas. Está orientada al objetivo, que es muy importante. Tiene como oportunidad de mejora el manejo de conflictos laborales.",
        "grupo_ocupasional": "4",
        "comunicacion": "19",
        "liderazgo": "19",
        "trabajo_en_equipo": "19",
        "productividad": "17",
        "flexibilidad": "19",
        "iniciativa": "15",
        "tolerancia_presion": "17",
        "planificacion_organizacion": "19",
        "puntaje_competencia": "125",
        "nota_competencia": "19",
        "categoria_competencia": "19",
        "categoria_objetivo": "Claramente por encima de lo esperado",
        "nota_objetivo": "19",
        "promedio": "19",
        "nota_objetivo1": "19",
        "nota_objetivo2": "19",
        "nivel_general": "Excelente",
        "nivel_general_nota": "19",
        "evaluador": "Se debe completar",
        "razon_social": "MP"
    },
    {
        "fecha_resolucion": "11/3/2022 17:34:09",
        "area": "FINANZAS",
        "nombre": "GAITAN LOPEZ, LUIS DANIEL",
        "correo": "lgaitan@marco.com.pe",
        "jefe_directo": "José Carlos Granda",
        "cargo": "ANALISTA DE PLANEAMIENTO FINANCIERO Y CONTROL DE GESTION",
        "fecha_evaluacion": "03/11/2022",
        "competencia_comunicacion": "Destacado",
        "competencia_trabajo_equipo": "Excelente",
        "competencia_productividad": "Excelente",
        "competencia_flexibilidad": "Excelente",
        "competencia_iniciativa": "Excelente",
        "competencia_tolerancia_presion": "Excelente",
        "competencia_planificacion_organizacion": "Excelente",
        "feedback_objetivo": "Claramente por encima de lo esperado: Frecuentemente supera los objetivos propuestos para su puesto. Muestra un desempeño que en diversos momentos es destacado.",
        "feedback_comentario": "Cuenta con excelentes habilidades técnicas y de análisis.",
        "grupo_ocupasional": "4",
        "comunicacion": "17",
        "liderazgo": "19",
        "trabajo_en_equipo": "19",
        "productividad": "19",
        "flexibilidad": "19",
        "iniciativa": "19",
        "tolerancia_presion": "19",
        "planificacion_organizacion": "19",
        "puntaje_competencia": "131",
        "nota_competencia": "19",
        "categoria_competencia": "19",
        "categoria_objetivo": "Claramente por encima de lo esperado",
        "nota_objetivo": "19",
        "promedio": "19",
        "nota_objetivo1": "19",
        "nota_objetivo2": "19",
        "nivel_general": "Excelente",
        "nivel_general_nota": "19",
        "evaluador": "Se debe completar",
        "razon_social": "MP"
    },
    {
        "fecha_resolucion": "11/4/2022 15:56:21",
        "area": "VENTAS TECHNIDRILL",
        "nombre": "MARCOS CHIPANA, WALTER DAVID",
        "correo": "wmarcos@marco.com.pe",
        "jefe_directo": "Ricardo Velarde",
        "cargo": "ASESOR TECNICO - LINEA TECHNIDRIL Y TRANS. DE POTENCIA",
        "fecha_evaluacion": "04/11/2022",
        "competencia_comunicacion": "Excelente",
        "competencia_trabajo_equipo": "Excelente",
        "competencia_productividad": "Destacado",
        "competencia_flexibilidad": "Excelente",
        "competencia_iniciativa": "Destacado",
        "competencia_tolerancia_presion": "Destacado",
        "competencia_planificacion_organizacion": "Destacado",
        "feedback_objetivo": "Claramente por encima de lo esperado: Frecuentemente supera los objetivos propuestos para su puesto. Muestra un desempeño que en diversos momentos es destacado.",
        "feedback_comentario": "Walter, es un profesional que se ha adaptado muy bien al entorno de trabajo de Marco Peruana. Tiene muchas habilidades de comunicación , capacidad y conocimiento técnico muy amplio, por lo que tiene mucho potencial para crecer aún más.. Profundizando mas su conocimiento en los temas tecnicos de todos los productos, podrá alcanzar los objetivos que se tiene para el.",
        "grupo_ocupasional": "4",
        "comunicacion": "19",
        "liderazgo": "19",
        "trabajo_en_equipo": "17",
        "productividad": "19",
        "flexibilidad": "17",
        "iniciativa": "17",
        "tolerancia_presion": "17",
        "planificacion_organizacion": "19",
        "puntaje_competencia": "125",
        "nota_competencia": "19",
        "categoria_competencia": "19",
        "categoria_objetivo": "Claramente por encima de lo esperado",
        "nota_objetivo": "19",
        "promedio": "19",
        "nota_objetivo1": "19",
        "nota_objetivo2": "19",
        "nivel_general": "Excelente",
        "nivel_general_nota": "19",
        "evaluador": "Se debe completar",
        "razon_social": "MP"
    },
    {
        "fecha_resolucion": "11/4/2022 19:13:33",
        "area": "CONTABILIDAD",
        "nombre": "VILLANUEVA MARTINEZ, CLARA ANGELA",
        "correo": "cvillanueva@marco.com.pe",
        "jefe_directo": "Rocío Rodriguez",
        "cargo": "ANALISTA SENIOR CONTABLE",
        "fecha_evaluacion": "04/11/2022",
        "competencia_comunicacion": "Destacado",
        "competencia_trabajo_equipo": "Cumple",
        "competencia_productividad": "Cumple",
        "competencia_flexibilidad": "Destacado",
        "competencia_iniciativa": "Cumple",
        "competencia_tolerancia_presion": "Cumple",
        "competencia_planificacion_organizacion": "Cumple",
        "feedback_objetivo": "Ligeramente por encima de lo esperado: En ocasiones supera los objetivos propuestos para su puesto. Muestra un desempeño satisfactorio con algunas oportunidades de logro.",
        "feedback_comentario": "",
        "grupo_ocupasional": "4",
        "comunicacion": "17",
        "liderazgo": "15",
        "trabajo_en_equipo": "15",
        "productividad": "17",
        "flexibilidad": "15",
        "iniciativa": "15",
        "tolerancia_presion": "15",
        "planificacion_organizacion": "17",
        "puntaje_competencia": "109",
        "nota_competencia": "17",
        "categoria_competencia": "17",
        "categoria_objetivo": "Ligeramente por encima de lo esperado",
        "nota_objetivo": "17",
        "promedio": "17",
        "nota_objetivo1": "17",
        "nota_objetivo2": "17",
        "nivel_general": "Destacado",
        "nivel_general_nota": "17",
        "evaluador": "Se debe completar",
        "razon_social": "MP"
    },
    {
        "fecha_resolucion": "11/8/2022 15:21:00",
        "area": "ALMACEN",
        "nombre": "FURA CABRERA, EDER RODRIGO",
        "correo": "efura@marco.com.pe",
        "jefe_directo": "Celso Condori",
        "cargo": "RESPONSABLE DE LOGISTICA",
        "fecha_evaluacion": "04/11/2022",
        "competencia_comunicacion": "Cumple",
        "competencia_trabajo_equipo": "Destacado",
        "competencia_productividad": "Destacado",
        "competencia_flexibilidad": "Destacado",
        "competencia_iniciativa": "Cumple",
        "competencia_tolerancia_presion": "Destacado",
        "competencia_planificacion_organizacion": "Destacado",
        "feedback_objetivo": "Ligeramente por encima de lo esperado: En ocasiones supera los objetivos propuestos para su puesto. Muestra un desempeño satisfactorio con algunas oportunidades de logro.",
        "feedback_comentario": "Gracias por el compromiso Eder ¡Sigamos así!",
        "grupo_ocupasional": "4",
        "comunicacion": "15",
        "liderazgo": "17",
        "trabajo_en_equipo": "17",
        "productividad": "17",
        "flexibilidad": "15",
        "iniciativa": "17",
        "tolerancia_presion": "17",
        "planificacion_organizacion": "17",
        "puntaje_competencia": "115",
        "nota_competencia": "17",
        "categoria_competencia": "17",
        "categoria_objetivo": "Ligeramente por encima de lo esperado",
        "nota_objetivo": "17",
        "promedio": "17",
        "nota_objetivo1": "17",
        "nota_objetivo2": "17",
        "nivel_general": "Destacado",
        "nivel_general_nota": "17",
        "evaluador": "Se debe completar",
        "razon_social": "MP"
    },
    {
        "fecha_resolucion": "11/8/2022 15:23:39",
        "area": "ALMACEN",
        "nombre": "CALIZAYA CHATA, NELLY MERCEDES",
        "correo": "ncalizaya@marco.com.pe",
        "jefe_directo": "Celso Condori",
        "cargo": "ENCARGADO DE ALMACEN",
        "fecha_evaluacion": "04/11/2022",
        "competencia_comunicacion": "Cumple",
        "competencia_trabajo_equipo": "Cumple",
        "competencia_productividad": "Destacado",
        "competencia_flexibilidad": "Cumple",
        "competencia_iniciativa": "Cumple",
        "competencia_tolerancia_presion": "Destacado",
        "competencia_planificacion_organizacion": "Destacado",
        "feedback_objetivo": "Cumple con lo requerido: Cumple con los objetivos propuestos para su puesto. Muestra un desempeño esperado.",
        "feedback_comentario": "Gracias por el compromiso Nelly ¡sigamos adelante!",
        "grupo_ocupasional": "4",
        "comunicacion": "15",
        "liderazgo": "15",
        "trabajo_en_equipo": "17",
        "productividad": "15",
        "flexibilidad": "15",
        "iniciativa": "17",
        "tolerancia_presion": "17",
        "planificacion_organizacion": "15",
        "puntaje_competencia": "111",
        "nota_competencia": "17",
        "categoria_competencia": "17",
        "categoria_objetivo": "Cumple con lo requerido",
        "nota_objetivo": "15",
        "promedio": "17",
        "nota_objetivo1": "16",
        "nota_objetivo2": "16",
        "nivel_general": "Destacado",
        "nivel_general_nota": "17",
        "evaluador": "Se debe completar",
        "razon_social": "MP"
    },
    {
        "fecha_resolucion": "11/8/2022 18:00:23",
        "area": "CALIDAD Y SEGURIDAD",
        "nombre": "CAYATA ENRIQUEZ, JENNIFER",
        "correo": "jcayata@marco.com.pe",
        "jefe_directo": "Yerick Ordaya",
        "cargo": "ANALISTA HSEQ Y CUMPLIMIENTO",
        "fecha_evaluacion": "08/11/2022",
        "competencia_comunicacion": "Destacado",
        "competencia_trabajo_equipo": "Destacado",
        "competencia_productividad": "Destacado",
        "competencia_flexibilidad": "Cumple",
        "competencia_iniciativa": "Cumple",
        "competencia_tolerancia_presion": "Destacado",
        "competencia_planificacion_organizacion": "Cumple",
        "feedback_objetivo": "Ligeramente por encima de lo esperado: En ocasiones supera los objetivos propuestos para su puesto. Muestra un desempeño satisfactorio con algunas oportunidades de logro.",
        "feedback_comentario": "Jennifer se encuentra aún en proceso de aprendizaje. Ha logrado acoplarse bien al grupo y entender los procesos complejos de Marco; pero aún no logramos encaminar efectivamente el cambio cultural hacia la mejora de los procesos. Requerimos más tiempo y esfuerzo.",
        "grupo_ocupasional": "4",
        "comunicacion": "17",
        "liderazgo": "17",
        "trabajo_en_equipo": "17",
        "productividad": "15",
        "flexibilidad": "15",
        "iniciativa": "17",
        "tolerancia_presion": "15",
        "planificacion_organizacion": "17",
        "puntaje_competencia": "113",
        "nota_competencia": "17",
        "categoria_competencia": "17",
        "categoria_objetivo": "Ligeramente por encima de lo esperado",
        "nota_objetivo": "17",
        "promedio": "17",
        "nota_objetivo1": "17",
        "nota_objetivo2": "17",
        "nivel_general": "Destacado",
        "nivel_general_nota": "17",
        "evaluador": "Se debe completar",
        "razon_social": "MP"
    },
    {
        "fecha_resolucion": "11/9/2022 9:41:08",
        "area": "SISTEMAS",
        "nombre": "ZARATE MEZA, ARTHUR YAMPHIER",
        "correo": "yzarate@marco.com.pe",
        "jefe_directo": "Armando Ochoa",
        "cargo": "ADMINISTRADOR DE REDES Y SOPORTE",
        "fecha_evaluacion": "09/11/2020",
        "competencia_comunicacion": "Destacado",
        "competencia_trabajo_equipo": "Destacado",
        "competencia_productividad": "Destacado",
        "competencia_flexibilidad": "Destacado",
        "competencia_iniciativa": "Destacado",
        "competencia_tolerancia_presion": "Cumple",
        "competencia_planificacion_organizacion": "Destacado",
        "feedback_objetivo": "Cumple con lo requerido: Cumple con los objetivos propuestos para su puesto. Muestra un desempeño esperado.",
        "feedback_comentario": "Es Responsable, Proactivo y tiene muchas iniciativa; lo que le falta mejorar es la comunicación.",
        "grupo_ocupasional": "4",
        "comunicacion": "17",
        "liderazgo": "17",
        "trabajo_en_equipo": "17",
        "productividad": "17",
        "flexibilidad": "17",
        "iniciativa": "15",
        "tolerancia_presion": "17",
        "planificacion_organizacion": "15",
        "puntaje_competencia": "117",
        "nota_competencia": "17",
        "categoria_competencia": "17",
        "categoria_objetivo": "Cumple con lo requerido",
        "nota_objetivo": "15",
        "promedio": "17",
        "nota_objetivo1": "16",
        "nota_objetivo2": "16",
        "nivel_general": "Destacado",
        "nivel_general_nota": "17",
        "evaluador": "Se debe completar",
        "razon_social": "MP"
    },
    {
        "fecha_resolucion": "11/16/2022 10:06:57",
        "area": "ALMACEN",
        "nombre": "ACEVEDO RAGUAY, EDWIN ABRAHAN",
        "correo": "eacevedo@marco.com.pe",
        "jefe_directo": "José David Ramos",
        "cargo": "ANALISTA DE TRANSPORTE Y DISTRIBUCION",
        "fecha_evaluacion": "16/11/2022",
        "competencia_comunicacion": "Cumple Parcialmente",
        "competencia_trabajo_equipo": "Debajo de lo esperado",
        "competencia_productividad": "Cumple",
        "competencia_flexibilidad": "Cumple",
        "competencia_iniciativa": "Cumple Parcialmente",
        "competencia_tolerancia_presion": "Destacado",
        "competencia_planificacion_organizacion": "Cumple",
        "feedback_objetivo": "Cumple con lo requerido: Cumple con los objetivos propuestos para su puesto. Muestra un desempeño esperado.",
        "feedback_comentario": "Edwin es una persona que viene desarrollando sus labores de manera eficiente, realiza las coordinaciones con los proveedores casi siempre de manera oportuna y cumple con la mayoría de objetivos trazados para su puesto, sin embargo, es una persona poca o muy poca comunicativa, muy introvertida, no tiene intención o deseo en trabajar en equipo para la mejora del proceso, en ocasiones no informa sobre situaciones importantes que como equipo. debemos tener conocimiento para poder darle el soporte necesario.",
        "grupo_ocupasional": "4",
        "comunicacion": "13",
        "liderazgo": "11",
        "trabajo_en_equipo": "15",
        "productividad": "15",
        "flexibilidad": "13",
        "iniciativa": "17",
        "tolerancia_presion": "15",
        "planificacion_organizacion": "15",
        "puntaje_competencia": "99",
        "nota_competencia": "15",
        "categoria_competencia": "15",
        "categoria_objetivo": "Cumple con lo requerido",
        "nota_objetivo": "15",
        "promedio": "15",
        "nota_objetivo1": "15",
        "nota_objetivo2": "15",
        "nivel_general": "Cumple",
        "nivel_general_nota": "15",
        "evaluador": "Se debe completar",
        "razon_social": "MP"
    },
    {
        "fecha_resolucion": "11/16/2022 10:35:56",
        "area": "ALMACEN",
        "nombre": "CHICOMA LECTOR, DIEGO MARTIN",
        "correo": "dchicoma@marco.com.pe",
        "jefe_directo": "José David Ramos",
        "cargo": "ANALISTA DE INVENTARIO",
        "fecha_evaluacion": "16/11/2022",
        "competencia_comunicacion": "Cumple",
        "competencia_trabajo_equipo": "Cumple",
        "competencia_productividad": "Cumple Parcialmente",
        "competencia_flexibilidad": "Cumple Parcialmente",
        "competencia_iniciativa": "Cumple Parcialmente",
        "competencia_tolerancia_presion": "Cumple",
        "competencia_planificacion_organizacion": "Cumple",
        "feedback_objetivo": "Ligeramente por debajo de lo esperado: No cumple con algunos de los objetivos propuestos para su puesto. Muestra un desempeño básico con errores.",
        "feedback_comentario": "Diego es un persona empeñosa, responsable y colaboradora, sin embargo, en lo que corresponde a sus tareas y funciones ha tenido varias observaciones, las cuales se han detectado tiempo después, y esto, porque no las informa en su debido momento. Estas observaciones han llevado a que tenga que revisar varias de las operaciones que viene realizando, ya que se tiene cierta desconfianza en la información que brinda.",
        "grupo_ocupasional": "4",
        "comunicacion": "15",
        "liderazgo": "15",
        "trabajo_en_equipo": "13",
        "productividad": "13",
        "flexibilidad": "13",
        "iniciativa": "15",
        "tolerancia_presion": "15",
        "planificacion_organizacion": "13",
        "puntaje_competencia": "99",
        "nota_competencia": "15",
        "categoria_competencia": "15",
        "categoria_objetivo": "Ligeramente por debajo de lo esperado",
        "nota_objetivo": "13",
        "promedio": "15",
        "nota_objetivo1": "14",
        "nota_objetivo2": "14",
        "nivel_general": "Cumple",
        "nivel_general_nota": "15",
        "evaluador": "Se debe completar",
        "razon_social": "MP"
    },
    {
        "fecha_resolucion": "11/22/2022 13:47:05",
        "area": "GERENCIA HIDRAULICA",
        "nombre": "AYZANOA ALCA, JOAQUIN RENATO",
        "correo": "rayzanoa@marco.com.pe",
        "jefe_directo": "Fernando Lozano",
        "cargo": "ANALISTA DE INTELIGENCIA DE NEGOCIOS",
        "fecha_evaluacion": "22/11/2022",
        "competencia_comunicacion": "Destacado",
        "competencia_trabajo_equipo": "Destacado",
        "competencia_productividad": "Excelente",
        "competencia_flexibilidad": "Excelente",
        "competencia_iniciativa": "Excelente",
        "competencia_tolerancia_presion": "Destacado",
        "competencia_planificacion_organizacion": "Destacado",
        "feedback_objetivo": "Claramente por encima de lo esperado: Frecuentemente supera los objetivos propuestos para su puesto. Muestra un desempeño que en diversos momentos es destacado.",
        "feedback_comentario": "Joaquin es un talento en la organización y debemos buscar su retención.",
        "grupo_ocupasional": "4",
        "comunicacion": "17",
        "liderazgo": "17",
        "trabajo_en_equipo": "19",
        "productividad": "19",
        "flexibilidad": "19",
        "iniciativa": "17",
        "tolerancia_presion": "17",
        "planificacion_organizacion": "19",
        "puntaje_competencia": "125",
        "nota_competencia": "19",
        "categoria_competencia": "19",
        "categoria_objetivo": "Claramente por encima de lo esperado",
        "nota_objetivo": "19",
        "promedio": "19",
        "nota_objetivo1": "19",
        "nota_objetivo2": "19",
        "nivel_general": "Excelente",
        "nivel_general_nota": "19",
        "evaluador": "Se debe completar",
        "razon_social": "MP"
    },
    {
        "fecha_resolucion": "12/5/2022 9:06:53",
        "area": "RRHH",
        "nombre": "TORRES ATAUPILLCO, IVETTE",
        "correo": "itorres@marco.com.pe",
        "jefe_directo": "Jeanete Rojas",
        "cargo": "ANALISTA DE PLANILLA",
        "fecha_evaluacion": "05/12/2022",
        "competencia_comunicacion": "Destacado",
        "competencia_trabajo_equipo": "Destacado",
        "competencia_productividad": "Destacado",
        "competencia_flexibilidad": "Destacado",
        "competencia_iniciativa": "Destacado",
        "competencia_tolerancia_presion": "Destacado",
        "competencia_planificacion_organizacion": "Destacado",
        "feedback_objetivo": "Ligeramente por encima de lo esperado: En ocasiones supera los objetivos propuestos para su puesto. Muestra un desempeño satisfactorio con algunas oportunidades de logro.",
        "feedback_comentario": "Rescato su orden y planificación, conoce sus oportunidades de mejora y se anticipa ante ellas.",
        "grupo_ocupasional": "4",
        "comunicacion": "17",
        "liderazgo": "17",
        "trabajo_en_equipo": "17",
        "productividad": "17",
        "flexibilidad": "17",
        "iniciativa": "17",
        "tolerancia_presion": "17",
        "planificacion_organizacion": "17",
        "puntaje_competencia": "119",
        "nota_competencia": "17",
        "categoria_competencia": "17",
        "categoria_objetivo": "Ligeramente por encima de lo esperado",
        "nota_objetivo": "17",
        "promedio": "17",
        "nota_objetivo1": "17",
        "nota_objetivo2": "17",
        "nivel_general": "Destacado",
        "nivel_general_nota": "17",
        "evaluador": "Se debe completar",
        "razon_social": "MP"
    },
    {
        "fecha_resolucion": "12/5/2022 9:10:01",
        "area": "RRHH",
        "nombre": "BURGOS MARCA, ROSALYNN CONSUELO",
        "correo": "rburgos@marco.com.pe",
        "jefe_directo": "Jeanete Rojas",
        "cargo": "TRABAJADORA SOCIAL",
        "fecha_evaluacion": "05/12/2022",
        "competencia_comunicacion": "Cumple",
        "competencia_trabajo_equipo": "Destacado",
        "competencia_productividad": "Destacado",
        "competencia_flexibilidad": "Destacado",
        "competencia_iniciativa": "Destacado",
        "competencia_tolerancia_presion": "Destacado",
        "competencia_planificacion_organizacion": "Destacado",
        "feedback_objetivo": "Ligeramente por encima de lo esperado: En ocasiones supera los objetivos propuestos para su puesto. Muestra un desempeño satisfactorio con algunas oportunidades de logro.",
        "feedback_comentario": "Como oportunidad de mejora es la comunicación con su jefatura, tener mas al tanto a su jefatura sobre sus actividades, información sobre el personal y coordinaciones.",
        "grupo_ocupasional": "4",
        "comunicacion": "15",
        "liderazgo": "17",
        "trabajo_en_equipo": "17",
        "productividad": "17",
        "flexibilidad": "17",
        "iniciativa": "17",
        "tolerancia_presion": "17",
        "planificacion_organizacion": "17",
        "puntaje_competencia": "117",
        "nota_competencia": "17",
        "categoria_competencia": "17",
        "categoria_objetivo": "Ligeramente por encima de lo esperado",
        "nota_objetivo": "17",
        "promedio": "17",
        "nota_objetivo1": "17",
        "nota_objetivo2": "17",
        "nivel_general": "Destacado",
        "nivel_general_nota": "17",
        "evaluador": "Se debe completar",
        "razon_social": "MP"
    },
    {
        "fecha_resolucion": "12/5/2022 10:42:41",
        "area": "RRHH",
        "nombre": "RAMOS RODAS, NATALIA",
        "correo": "nramos@marco.com.pe",
        "jefe_directo": "Jeanete Rojas",
        "cargo": "ANALISTA DE GESTION Y DESARROLLO",
        "fecha_evaluacion": "05/12/2022",
        "competencia_comunicacion": "Cumple",
        "competencia_trabajo_equipo": "Cumple",
        "competencia_productividad": "Destacado",
        "competencia_flexibilidad": "Cumple",
        "competencia_iniciativa": "Destacado",
        "competencia_tolerancia_presion": "Destacado",
        "competencia_planificacion_organizacion": "Cumple",
        "feedback_objetivo": "Ligeramente por encima de lo esperado: En ocasiones supera los objetivos propuestos para su puesto. Muestra un desempeño satisfactorio con algunas oportunidades de logro.",
        "feedback_comentario": "Hace un buen trabajo, aunque a veces se recarga en tareas que podrían no corresponderle y delegar inmediatamente a la compañera o área que le corresponde.",
        "grupo_ocupasional": "4",
        "comunicacion": "15",
        "liderazgo": "15",
        "trabajo_en_equipo": "17",
        "productividad": "15",
        "flexibilidad": "17",
        "iniciativa": "17",
        "tolerancia_presion": "15",
        "planificacion_organizacion": "17",
        "puntaje_competencia": "111",
        "nota_competencia": "17",
        "categoria_competencia": "17",
        "categoria_objetivo": "Ligeramente por encima de lo esperado",
        "nota_objetivo": "17",
        "promedio": "17",
        "nota_objetivo1": "17",
        "nota_objetivo2": "17",
        "nivel_general": "Destacado",
        "nivel_general_nota": "17",
        "evaluador": "Se debe completar",
        "razon_social": "MP"
    },
    {
        "fecha_resolucion": "1/12/2023 12:20:23",
        "area": "LUBRICACION INDUSTRIAL",
        "nombre": "AGUIRRE VASQUEZ, JOSUE EZEQUIEL",
        "correo": "jaguirre@marco.com.pe",
        "jefe_directo": "Franz Rivas",
        "cargo": "INGENIERO LIDER",
        "fecha_evaluacion": "12/01/2023",
        "competencia_comunicacion": "Destacado",
        "competencia_trabajo_equipo": "Destacado",
        "competencia_productividad": "Destacado",
        "competencia_flexibilidad": "Destacado",
        "competencia_iniciativa": "Destacado",
        "competencia_tolerancia_presion": "Destacado",
        "competencia_planificacion_organizacion": "Destacado",
        "feedback_objetivo": "Claramente por encima de lo esperado: Frecuentemente supera los objetivos propuestos para su puesto. Muestra un desempeño que en diversos momentos es destacado.",
        "feedback_comentario": "Josue, realiza un buen trabajo en equipo!",
        "grupo_ocupasional": "4",
        "comunicacion": "17",
        "liderazgo": "17",
        "trabajo_en_equipo": "17",
        "productividad": "17",
        "flexibilidad": "17",
        "iniciativa": "17",
        "tolerancia_presion": "17",
        "planificacion_organizacion": "19",
        "puntaje_competencia": "119",
        "nota_competencia": "17",
        "categoria_competencia": "17",
        "categoria_objetivo": "Claramente por encima de lo esperado",
        "nota_objetivo": "19",
        "promedio": "17",
        "nota_objetivo1": "18",
        "nota_objetivo2": "18",
        "nivel_general": "Excelente",
        "nivel_general_nota": "19",
        "evaluador": "Se debe completar",
        "razon_social": "MP"
    },
    {
        "fecha_resolucion": "1/19/2023 13:04:37",
        "area": "SISTEMAS DE LUBRICACION",
        "nombre": "OLAECHEA CUSTODIO, DANTE",
        "correo": "dolaechea@marco.com.pe",
        "jefe_directo": "Diego Tafur",
        "cargo": "INGENIERO LIDER",
        "fecha_evaluacion": "19/01/2023",
        "competencia_comunicacion": "Excelente",
        "competencia_trabajo_equipo": "Excelente",
        "competencia_productividad": "Excelente",
        "competencia_flexibilidad": "Destacado",
        "competencia_iniciativa": "Destacado",
        "competencia_tolerancia_presion": "Excelente",
        "competencia_planificacion_organizacion": "Excelente",
        "feedback_objetivo": "Claramente por encima de lo esperado: Frecuentemente supera los objetivos propuestos para su puesto. Muestra un desempeño que en diversos momentos es destacado.",
        "feedback_comentario": "Gran labor profesional, espero que podamos plantear juntos metas aun mas ambiciosas con iniciativa compartida",
        "grupo_ocupasional": "4",
        "comunicacion": "19",
        "liderazgo": "19",
        "trabajo_en_equipo": "19",
        "productividad": "17",
        "flexibilidad": "17",
        "iniciativa": "19",
        "tolerancia_presion": "19",
        "planificacion_organizacion": "19",
        "puntaje_competencia": "129",
        "nota_competencia": "19",
        "categoria_competencia": "19",
        "categoria_objetivo": "Claramente por encima de lo esperado",
        "nota_objetivo": "19",
        "promedio": "19",
        "nota_objetivo1": "19",
        "nota_objetivo2": "19",
        "nivel_general": "Excelente",
        "nivel_general_nota": "19",
        "evaluador": "Se debe completar",
        "razon_social": "MP"
    }
]